pyop/__init__.py
pyop/access_token.py
pyop/authz_state.py
pyop/client_authentication.py
pyop/crypto.py
pyop/exceptions.py
pyop/message.py
pyop/provider.py
pyop/request_validator.py
pyop/storage.py
pyop/subject_identifier.py
pyop/userinfo.py
pyop/util.py
pyop-3.4.2.dist-info/LICENSE
pyop-3.4.2.dist-info/METADATA
pyop-3.4.2.dist-info/NOTICE
pyop-3.4.2.dist-info/WHEEL
pyop-3.4.2.dist-info/top_level.txt
pyop-3.4.2.dist-info/RECORD
