Metadata-Version: 2.1
Name: pyop
Version: 3.4.2
Summary: OpenID Connect Provider (OP) library in Python.
Home-page: https://github.com/IdentityPython/pyop
Author: Rebecka Gulliksson
Author-email: satosa-dev@lists.sunet.se
License: Apache 2.0
Platform: UNKNOWN
License-File: LICENSE
License-File: NOTICE
Requires-Dist: oic (>=1.2.1)
Requires-Dist: pycryptodomex
Provides-Extra: mongo
Requires-Dist: pymongo (<4.0,>=3.12) ; extra == 'mongo'
Provides-Extra: redis
Requires-Dist: redis ; extra == 'redis'
